e2tts.py
e2tts_mlx-0.0.4.dist-info/METADATA
e2tts_mlx-0.0.4.dist-info/WHEEL
e2tts_mlx-0.0.4.dist-info/entry_points.txt
e2tts_mlx-0.0.4.dist-info/top_level.txt
e2tts_mlx-0.0.4.dist-info/RECORD
